plone.event-2.0.3-py3.13-nspkg.pth
plone/event/__init__.py
plone/event/adapters.py
plone/event/configure.zcml
plone/event/interfaces.py
plone/event/recurrence.py
plone/event/recurrence.rst
plone/event/recurrence_dateutil.rst
plone/event/utils.py
plone/event/utils.rst
plone/event/tests/__init__.py
plone/event/tests/test_adapters.py
plone/event/tests/test_doctest.py
plone/event/tests/test_recurrence_int_sequence.py
plone/event/tests/test_recurrence_sequence_ical.py
plone/event/tests/test_recurrence_sequence_timedelta.py
plone/event/tests/test_utils.py
plone_event-2.0.3.dist-info/METADATA
plone_event-2.0.3.dist-info/WHEEL
plone_event-2.0.3.dist-info/namespace_packages.txt
plone_event-2.0.3.dist-info/top_level.txt
plone_event-2.0.3.dist-info/RECORD
