Metadata-Version: 2.4
Name: plone.event
Version: 2.0.3
Summary: Event and calendaring related tools not bound to Plone
Home-page: https://github.com/plone/plone.event
Author: Plone Foundation
Author-email: plone-developers@lists.sourceforge.net
License: GPL
Keywords: Plone calendar calendaring event recurring
Classifier: Development Status :: 5 - Production/Stable
Classifier: Framework :: Plone
Classifier: Framework :: Plone :: 6.0
Classifier: Framework :: Plone :: Core
Classifier: License :: OSI Approved :: GNU General Public License (GPL)
Classifier: Programming Language :: Python
Classifier: Programming Language :: Python :: 3.8
Classifier: Programming Language :: Python :: 3.9
Classifier: Programming Language :: Python :: 3.10
Classifier: Programming Language :: Python :: 3.11
Requires-Python: >=3.8
Requires-Dist: setuptools
Requires-Dist: python-dateutil
Requires-Dist: pytz
Requires-Dist: zope.component
Requires-Dist: zope.interface
Provides-Extra: test
Requires-Dist: DateTime; extra == "test"
Requires-Dist: zope.configuration; extra == "test"
Dynamic: author
Dynamic: author-email
Dynamic: classifier
Dynamic: description
Dynamic: description-content-type
Dynamic: home-page
Dynamic: keywords
Dynamic: license
Dynamic: provides-extra
Dynamic: requires-dist
Dynamic: requires-python
Dynamic: summary
